Workbook

Sheet Parquets
A1: # | B1: File | C1: Rows | D1: MB | E1: Geography | F1: Strata beyond age | G1: Time span | J1: Parquet | K1: Dataset
A2: 1 | B2: wisqars_state_age_demographics.parquet | C2: 91298 | D2: 0.26 | E2: state + national (52) | F2: sex, race, ethnicity | G2: 2001–2024, annual | J2: wisqars_state_age_demographics.parquet | K2: WISQARS
A3: 2 | B3: nhtsa_state_age_sex.parquet | C3: 7606 | D3: 0.02 | E3: state + national (52) | F3: sex | G3: 2000–2024, annual | J3: nhtsa_state_age_sex.parquet, nhtsa_county_age_sex.parquet | K3: NHTSA
A4: 3 | B4: nhtsa_county_age_sex.parquet | C4: 164160 | D4: 0.35 | E4: county (3,129) | F4: sex | G4: 2000–2024, annual | J4: yrbss_state_age_demographics.parquet | K4: YRBSS
A5: 4 | B5: yrbss_state_age_demographics.parquet | C5: 264600 | D5: 0.72 | E5: state + national (49) | F5: sex, race, ethnicity | G5: 2005–2023, biennial | J5: epic_injury_state_age_year.parquet, epic_injury_state_age_month.parquet | K5: Epic Injury
A6: 5 | B6: epic_injury_state_age_year.parquet | C6: 4992 | D6: 0.03 | E6: state + national (52) | F6: — | G6: 2018–2025, annual | J6: epic_chronic_state_age.parquet, epic_chronic_county_age.parquet, | K6: Epic Chronic
A7: 6 | B7: epic_injury_state_age_month.parquet | C7: 58005 | D7: 0.16 | E7: state + national (52) | F7: — | G7: 2018-01–2025-09, monthly | J7: medicaid_state_payer.parquet | K7: medicaid_quality
A8: 7 | B8: epic_chronic_state_age.parquet | C8: 2600 | D8: 0.01 | E8: state + national (52) | F8: — | G8: 2016–2025, annual | J8: chr_state.parquet, chr_county.parquet | K8: CHR
A9: 8 | B9: epic_chronic_county_age.parquet | C9: 47055 | D9: 0.27 | E9: county (3,137) | F9: — | G9: 2023–2025, annual | J9: noaa_heat_risk_state.parquet, noaa_heat_risk_county.parquet | K9: NOAA heat risk
A10: 9 | B10: medicaid_state_payer.parquet | C10: 5280 | D10: 0.03 | E10: state (51) | F10: payer, domain | G10: 2014–2023, annual | J10: immunizations_state_age_vaccine.parquet | K10: childhood immunization bundle
A11: 10 | B11: chr_state.parquet | C11: 15406 | D11: 0.11 | E11: state + national (52) | F11: — | G11: 2010–2025, annual
A12: 11 | B12: chr_county.parquet | C12: 884453 | D12: 5.53 | E12: county (3,159) | F12: — | G12: 2010–2025, annual
A13: 12 | B13: noaa_heat_risk_state.parquet | C13: 36500 | D13: 0.11 | E13: state (50) | F13: forecast_day | G13: 2024-08→2026-08, daily
A14: 13 | B14: noaa_heat_risk_county.parquet | C14: 2269570 | D14: 2.97 | E14: county (3,109) | F14: forecast_day | G14: 2024-08→2026-08, daily
A15: 14 | B15: immunizations_state_age_vaccine.parquet | C15: 47777 | D15: 0.25 | E15: state + national (52) | F15: vaccine | G15: 2011–2024, annual

Sheet Overview
A1: Section | B1: Focus area | C1: Dataset source | D1: Variables | E1: Parquet file
A2: Injury and violence | B2: Motor vehicle accidents | C2: WISQARS | D2: pedal_cyclist_mv_traffic, pedestrian_mv_traffic, motor_vehicle_traffic (_deaths_ and _rate_) | E2: =_xlfn.XLOOKUP(C2, Parquets!K$2:K$10, Parquets!J$2:J$10) -> wisqars_state_age_demographics.parquet
A3: Injury and violence | B3: Motor vehicle accidents | C3: NHTSA | D3: nhtsa_fatalities from data_age_sex | E3: =_xlfn.XLOOKUP(C3, Parquets!K$2:K$10, Parquets!J$2:J$10) -> nhtsa_state_age_sex.parquet, nhtsa_county_age_sex.parquet
A4: Injury and violence | B4: Dangerous driving | C4: YRBSS | D4: pct_no_seatbelt, pct_rode_drinking_driver, pct_drove_drinking, pct_text_while_driving | E4: =_xlfn.XLOOKUP(C4, Parquets!K$2:K$10, Parquets!J$2:J$10) -> yrbss_state_age_demographics.parquet
A5: Injury and violence | B5: Concussions | C5: YRBSS | D5: pct_sports_concussion | E5: =_xlfn.XLOOKUP(C5, Parquets!K$2:K$10, Parquets!J$2:J$10) -> yrbss_state_age_demographics.parquet
A6: Injury and violence | B6: Firearms | C6: WISQARS | D6: wisqars_rate_firearm_accident, wisqars_rate_firearm_homicide, wisqars_rate_firearm_suicide, wisqars_rate_firearm_intentional, wisqars_deaths_firearm_accident, wisqars_deaths_firearm_homicide, wisqars_deaths_firearm_suicide, wisqars_deaths_firearm_intentional | E6: =_xlfn.XLOOKUP(C6, Parquets!K$2:K$10, Parquets!J$2:J$10) -> wisqars_state_age_demographics.parquet
A7: Injury and violence | B7: Firearms | C7: Epic Injury | D7: epic_n_ed_firearm, epic_rate_ed_firearm | E7: =_xlfn.XLOOKUP(C7, Parquets!K$2:K$10, Parquets!J$2:J$10) -> epic_injury_state_age_year.parquet, epic_injury_state_age_month.parquet
A8: Injury and violence | B8: Firearms | C8: YRBSS | D8: pct_carried_weapon_school, pct_carried_gun, pct_threatened_weapon_school | E8: =_xlfn.XLOOKUP(C8, Parquets!K$2:K$10, Parquets!J$2:J$10) -> yrbss_state_age_demographics.parquet
A9: Substance abuse | B9: Substances used | C9: YRBSS | D9: pct_ever_cigarette pct_ever_vape pct_current_smokeless_tobacco pct_current_alcohol pct_binge_drinking pct_ever_marijuana pct_early_marijuana pct_current_marijuana pct_ever_rx_opioid_misuse pct_current_rx_opioid_misuse pct_ever_cocaine pct_ever_inhalants pct_ever_heroin pct_ever_methamphetamines pct_ever_ecstasy pct_ever_hallucinogens pct_ever_inject_drug pct_ever_illicit_drug | E9: =_xlfn.XLOOKUP(C9, Parquets!K$2:K$10, Parquets!J$2:J$10) -> yrbss_state_age_demographics.parquet
A10: Substance abuse | B10: Overdose trends | C10: WISQARS | D10: wisqars_deaths_drug_poisoning, wisqars_rate_drug_poisoning | E10: =_xlfn.XLOOKUP(C10, Parquets!K$2:K$10, Parquets!J$2:J$10) -> wisqars_state_age_demographics.parquet
A11: Substance abuse | B11: Overdose trends | C11: Epic injury | D11: epic_rate_ed_opioid, epic_n_ed_opioid | E11: =_xlfn.XLOOKUP(C11, Parquets!K$2:K$10, Parquets!J$2:J$10) -> epic_injury_state_age_year.parquet, epic_injury_state_age_month.parquet
A12: Substance abuse | B12: Follow up for ED visits for drug/alcohol related reasons | C12: medicaid_quality | D12: medicaid_fua_ch_30d_rate, medicaid_fua_ch_7d_rate | E12: =_xlfn.XLOOKUP(C12, Parquets!K$2:K$10, Parquets!J$2:J$10) -> medicaid_state_payer.parquet
A13: Mental health | B13: Suicide and suiciadal ideation | C13: YRBSS | D13: pct_considered_suicide, pct_planned_suicide, pct_attempted_suicide, pct_injurious_suicide_attempt | E13: =_xlfn.XLOOKUP(C13, Parquets!K$2:K$10, Parquets!J$2:J$10) -> yrbss_state_age_demographics.parquet
... A29: Preventative health and wellness | B29: Preventative health | C29: medicaid_quality | D29: medicaid_ima_ch_rate, medicaid_w34_ch_rate, medicaid_awc_ch_rate, medicaid_w15_ch_rate, medicaid_w30_ch_rate, medicaid_oev_ch_rate, medicaid_cap_ch_rate, medicaid_dev_ch_rate | E29: =_xlfn.XLOOKUP(C29, Parquets!K$2:K$10, Parquets!J$2:J$10) -> medicaid_state_payer.parquet
A30: Preventative health and wellness | B30: Vaccinations | C30: Childhood immunization bundle | E30: =_xlfn.XLOOKUP(C30, Parquets!K$2:K$10, Parquets!J$2:J$10) -> immunizations_state_age_vaccine.parquet
A31: Preventative health and wellness | B31: Activity levels | C31: YRBSS | D31: pct_inactive_60min_5days, pct_no_pe_classes, pct_no_sports_team, pct_no_daily_pe, pct_inactive_all_days | E31: =_xlfn.XLOOKUP(C31, Parquets!K$2:K$10, Parquets!J$2:J$10) -> yrbss_state_age_demographics.parquet
A32: Preventative health and wellness | B32: Nutrition | C32: YRBSS | D32: pct_no_breakfast, pct_no_breakfast_7days, pct_no_fruit, pct_no_vegetables | E32: =_xlfn.XLOOKUP(C32, Parquets!K$2:K$10, Parquets!J$2:J$10) -> yrbss_state_age_demographics.parquet
A33: Preventative health and wellness | B33: Nutrition | C33: medicaid_quality | D33: medicaid_wcc_ch_rate | E33: =_xlfn.XLOOKUP(C33, Parquets!K$2:K$10, Parquets!J$2:J$10) -> medicaid_state_payer.parquet
A34: Preventative health and wellness | B34: Nutrition | C34: CHR | D34: chr_limited_access_to_healthy_foods, chr_food_environment_index | E34: =_xlfn.XLOOKUP(C34, Parquets!K$2:K$10, Parquets!J$2:J$10) -> chr_state.parquet, chr_county.parquet
A35: Social determinants of health | B35: Schools | C35: CHR | D35: chr_high_school_completion, chr_school_segregation, chr_school_funding_adequacy, chr_child_care_centers, chr_high_school_graduation, chr_math_scores, chr_reading_scores | E35: =_xlfn.XLOOKUP(C35, Parquets!K$2:K$10, Parquets!J$2:J$10) -> chr_state.parquet, chr_county.parquet
A36: Social determinants of health | B36: Access to care | C36: CHR | D36: chr_uninsured_children, chr_primary_care_physicians, chr_inadequate_social_support, chr_other_primary_care_providers | E36: =_xlfn.XLOOKUP(C36, Parquets!K$2:K$10, Parquets!J$2:J$10) -> chr_state.parquet, chr_county.parquet
A37: Social determinants of health | B37: Poverty measures | C37: CHR | D37: chr_children_in_poverty, chr_income_inequality, chr_food_insecurity, | E37: =_xlfn.XLOOKUP(C37, Parquets!K$2:K$10, Parquets!J$2:J$10) -> chr_state.parquet, chr_county.parquet
A38: Social determinants of health | B38: Housing | C38: CHR | D38: chr_single_parent_households, chr_high_housing_costs, chr_severe_housing_problems, chr_severe_housing_cost_burden | E38: =_xlfn.XLOOKUP(C38, Parquets!K$2:K$10, Parquets!J$2:J$10) -> chr_state.parquet, chr_county.parquet
A39: Social determinants of health | B39: Surrounding communtiy | C39: CHR | D39: chr_access_to_recreational_facilities, chr_limited_access_to_healthy_foods, chr_access_to_parks, chr_access_to_exercise_opportunities, chr_food_environment_index, chr_residential_segregation_black_white | E39: =_xlfn.XLOOKUP(C39, Parquets!K$2:K$10, Parquets!J$2:J$10) -> chr_state.parquet, chr_county.parquet
A40: Social determinants of health | B40: Crime/violence | C40: CHR | D40: chr_violent_crime, chr_juvenile_arrests, chr_firearm_fatalities | E40: =_xlfn.XLOOKUP(C40, Parquets!K$2:K$10, Parquets!J$2:J$10) -> chr_state.parquet, chr_county.parquet

Sheet Main page
A1: Focus area | B1: Dataset Source | C1: Details | D1: Geographic resolution | E1: Demographic resolution(s) *all have age unless noted | F1: Variables | G1: Parquet file(s) | H1: Notes
A2: What is injuring kids? | B2: NEISS | C2: Top X (5?) causes of injury by age group (1 month buckets for ages 0-2, 5 year age groups after) | D2: Only at national level | E2: age, sex
A3: What is making kids sick? | B3: Epic | C3: Top X (5?) chief complaints by age group (1 month buckets for ages 0-2, 5 year age groups after) at county level | E3: age
B4: CHR | C4: Infant mortality (chr_infant_mortality) and child mortality (chr_child_mortality) | D4: County | H4: Age baked in

Sheet Injury & violence
A1: Focus area | B1: Dataset Source | C1: Geographic resolution | D1: Demographic resolution(s) *all have age unless noted | E1: Variables | F1: Parquet file(s) | G1: Notes
A2: Motor vehicle accidents | B2: WISQARS | C2: State | D2: sex, race, ethnicity | E2: pedal_cyclist_mv_traffic, pedestrian_mv_traffic, motor_vehicle_traffic (_deaths_ and _rate_) | F2: =_xlfn.XLOOKUP(B2, Parquets!K$2:K$10, Parquets!J$2:J$10) -> wisqars_state_age_demographics.parquet
B3: NHTSA | C3: State | D3: sex | E3: nhtsa_fatalities from data_age_sex | F3: =_xlfn.XLOOKUP(B3, Parquets!K$2:K$10, Parquets!J$2:J$10) -> nhtsa_state_age_sex.parquet, nhtsa_county_age_sex.parquet
A4: Dangerous driving | B4: YRBSS | C4: State | D4: sex, race, ethnicity | E4: pct_no_seatbelt, pct_rode_drinking_driver, pct_drove_drinking, pct_text_while_driving | F4: =_xlfn.XLOOKUP(B4, Parquets!K$2:K$10, Parquets!J$2:J$10) -> yrbss_state_age_demographics.parquet
A5: Concussions | B5: YRBSS | C5: State | D5: sex, race, ethnicity | E5: pct_sports_concussion | F5: =_xlfn.XLOOKUP(B5, Parquets!K$2:K$10, Parquets!J$2:J$10) -> yrbss_state_age_demographics.parquet
B6: Epic | C6: State
A7: Firearms | B7: WISQARS | C7: State | D7: sex, race, ethnicity | E7: wisqars_rate_firearm_accident, wisqars_rate_firearm_homicide, wisqars_rate_firearm_suicide, wisqars_rate_firearm_intentional, wisqars_deaths_firearm_accident, wisqars_deaths_firearm_homicide, wisqars_deaths_firearm_suicide, wisqars_deaths_firearm_intentional | F7: =_xlfn.XLOOKUP(B7, Parquets!K$2:K$10, Parquets!J$2:J$10) -> wisqars_state_age_demographics.parquet
B8: Epic Injury | C8: State | E8: epic_n_ed_firearm, epic_rate_ed_firearm | F8: =_xlfn.XLOOKUP(B8, Parquets!K$2:K$10, Parquets!J$2:J$10) -> epic_injury_state_age_year.parquet, epic_injury_state_age_month.parquet
B9: YRBSS | C9: State | D9: sex, race, ethnicity | E9: pct_carried_weapon_school, pct_carried_gun, pct_threatened_weapon_school | F9: =_xlfn.XLOOKUP(B9, Parquets!K$2:K$10, Parquets!J$2:J$10) -> yrbss_state_age_demographics.parquet

Sheet Substance abuse
A1: Focus area | B1: Dataset Source | C1: Geographic resolution | D1: Demographic resolution(s) *all have age unless noted | E1: Variables | F1: Parquet file(s) | G1: Notes
A2: Substances used | B2: YRBSS | C2: State | D2: sex, race, ethnicity | E2: pct_ever_cigarette pct_ever_vape pct_current_smokeless_tobacco pct_current_alcohol pct_binge_drinking pct_ever_marijuana pct_early_marijuana pct_current_marijuana pct_ever_rx_opioid_misuse pct_current_rx_opioid_misuse pct_ever_cocaine pct_ever_inhalants pct_ever_heroin pct_ever_methamphetamines pct_ever_ecstasy pct_ever_hallucinogens pct_ever_inject_drug pct_ever_illicit_drug | F2: =_xlfn.XLOOKUP(B2, Parquets!K$2:K$10, Parquets!J$2:J$10) -> yrbss_state_age_demographics.parquet
A3: Overdose trends | B3: WISQARS | C3: State | D3: sex, race, ethnicity | E3: wisqars_deaths_drug_poisoning, wisqars_rate_drug_poisoning | F3: =_xlfn.XLOOKUP(B3, Parquets!K$2:K$10, Parquets!J$2:J$10) -> wisqars_state_age_demographics.parquet
B4: Epic Injury | C4: State | E4: epic_rate_ed_opioid, epic_n_ed_opioid | F4: =_xlfn.XLOOKUP(B4, Parquets!K$2:K$10, Parquets!J$2:J$10) -> epic_injury_state_age_year.parquet, epic_injury_state_age_month.parquet
A5: Follow up for ED visits for any drug/alcohol related reason | B5: medicaid_quality | C5: State | D5: sex, race, ethnicity | E5: medicaid_fua_ch_30d_rate, medicaid_fua_ch_7d_rate | F5: =_xlfn.XLOOKUP(B5, Parquets!K$2:K$10, Parquets!J$2:J$10) -> medicaid_state_payer.parquet

Sheet Mental health
A1: Focus area | B1: Dataset Source | C1: Geographic resolution | D1: Demographic resolution(s) *all have age unless noted | E1: Variables | F1: Parquet file(s) | G1: Notes
A2: Suicide and suiciadal ideation | B2: YRBSS | C2: State | D2: sex, race, ethnicity | E2: pct_considered_suicide, pct_planned_suicide, pct_attempted_suicide, pct_injurious_suicide_attempt | F2: =_xlfn.XLOOKUP(B2, Parquets!K$2:K$10, Parquets!J$2:J$10) -> yrbss_state_age_demographics.parquet
B3: Crisis text line
A4: Anxiety | B4: Crisis text line
A5: Bullying | B5: YRBSS | C5: State | D5: sex, race, ethnicity | E5: pct_bullied_at_school, pct_bullied_electronic | F5: =_xlfn.XLOOKUP(B5, Parquets!K$2:K$10, Parquets!J$2:J$10) -> yrbss_state_age_demographics.parquet
A6: Care seeking | B6: medicaid_quality | C6: State | D6: sex, race, ethnicity | E6: medicaid_fuh_ch_30d_rate, medicaid_fuh_ch_7d_rate | F6: =_xlfn.XLOOKUP(B6, Parquets!K$2:K$10, Parquets!J$2:J$10) -> medicaid_state_payer.parquet
B7: Epic | E7: ED visits for mental health ED visits for suicide Hospital admissions for suicide, depression, disordered eating, Length of stay in ED/discharge status
A8: General mental health measures | B8: YRBSS | C8: State | D8: sex, race, ethnicity | E8: pct_social_media_daily, pct_poor_mental_health, pct_insufficient_sleep, pct_not_close_at_school | F8: =_xlfn.XLOOKUP(B8, Parquets!K$2:K$10, Parquets!J$2:J$10) -> yrbss_state_age_demographics.parquet
B9: CHR | C9: County | E9: chr_disconnected_youth | F9: =_xlfn.XLOOKUP(B9, Parquets!K$2:K$10, Parquets!J$2:J$10) -> chr_state.parquet, chr_county.parquet | G9: age baked into variable

Sheet Chronic disease
A1: Focus area | B1: Dataset Source | C1: Geographic resolution | D1: Demographic resolution(s) *all have age unless noted | E1: Variables | F1: Parquet file(s) | G1: Notes
A2: Obesity | B2: Epic Chronic | C2: County (no time variable), state | E2: obesity_bmi, obesity_dx_ccw, n_patients_chronic | F2: =_xlfn.XLOOKUP(B2, Parquets!K$2:K$10, Parquets!J$2:J$10) -> epic_chronic_state_age.parquet, epic_chronic_county_age.parquet,
A3: Diabetes | B3: Epic Chronic | C3: County (no time variable), state | E3: diabetes_a1c_6_5, diabetes_dx_ccw | F3: =_xlfn.XLOOKUP(B3, Parquets!K$2:K$10, Parquets!J$2:J$10) -> epic_chronic_state_age.parquet, epic_chronic_county_age.parquet,
A4: Asthma | B4: medicaid_quality | D4: sex, race, ethnicity | E4: medicaid_mma_ch_rate, medicaid_amr_ch_rate | F4: =_xlfn.XLOOKUP(B4, Parquets!K$2:K$10, Parquets!J$2:J$10) -> medicaid_state_payer.parquet
A5: Lead testing | B5: medicaid_quality | D5: sex, race, ethnicity | E5: medicaid_lsc_ch_rate | F5: =_xlfn.XLOOKUP(B5, Parquets!K$2:K$10, Parquets!J$2:J$10) -> medicaid_state_payer.parquet
B6: CHR | E6: chr_lead_poisoned_children | F6: =_xlfn.XLOOKUP(B6, Parquets!K$2:K$10, Parquets!J$2:J$10) -> chr_state.parquet, chr_county.parquet | G6: Not age stratified
A7: Environmental health | B7: Epic Injury | C7: County (no time variable), state | E7: epic_rate_ed_heat, epic_n_ed_heat | F7: =_xlfn.XLOOKUP(B7, Parquets!K$2:K$10, Parquets!J$2:J$10) -> epic_injury_state_age_year.parquet, epic_injury_state_age_month.parquet
B8: CHR | C8: County | E8: chr_air_pollution_ozone_days, chr_air_pollution_particulate_matter_days, chr_contaminants_in_municipal_water_wi, chr_air_pollution_particulate_matter, chr_adverse_climate_events | F8: =_xlfn.XLOOKUP(B8, Parquets!K$2:K$10, Parquets!J$2:J$10) -> chr_state.parquet, chr_county.parquet | G8: Not age stratified
B9: NOAA heat risk | C9: County | E9: value, low_coverage_flag | F9: =_xlfn.XLOOKUP(B9, Parquets!K$2:K$10, Parquets!J$2:J$10) -> noaa_heat_risk_state.parquet, noaa_heat_risk_county.parquet | G9: Not age stratified

Sheet Preventive health & wellness
A1: Focus area | B1: Dataset Source | C1: Geographic resolution | D1: Demographic resolution(s) *all have age unless noted | E1: Variables | F1: Parquet file(s) | G1: Notes
A2: Pregnancy | B2: CHR | C2: County | E2: chr_teen_births | F2: =_xlfn.XLOOKUP(B2, Parquets!K$2:K$10, Parquets!J$2:J$10) -> chr_state.parquet, chr_county.parquet | G2: Age baked in
B3: medicaid_quality | C3: State | D3: sex, race, ethnicity | E3: medicaid_fpc_ch_rate, medicaid_ppc_ch_rate | F3: =_xlfn.XLOOKUP(B3, Parquets!K$2:K$10, Parquets!J$2:J$10) -> medicaid_state_payer.parquet
A4: Contraception | B4: medicaid_quality | C4: State | D4: sex, race, ethnicity | E4: medicaid_ccp_ch_rate | F4: =_xlfn.XLOOKUP(B4, Parquets!K$2:K$10, Parquets!J$2:J$10) -> medicaid_state_payer.parquet
A5: Preventative health | B5: medicaid_quality | C5: State | D5: sex, race, ethnicity | E5: medicaid_ima_ch_rate, medicaid_w34_ch_rate, medicaid_awc_ch_rate, medicaid_w15_ch_rate, medicaid_w30_ch_rate, medicaid_oev_ch_rate, medicaid_cap_ch_rate, medicaid_dev_ch_rate | F5: =_xlfn.XLOOKUP(B5, Parquets!K$2:K$10, Parquets!J$2:J$10) -> medicaid_state_payer.parquet
A6: Vaccinations | B6: childhood immunization bundle | F6: =_xlfn.XLOOKUP(B6, Parquets!K$2:K$10, Parquets!J$2:J$10) -> immunizations_state_age_vaccine.parquet
A7: Activity levels | B7: YRBSS | C7: State | D7: sex, race, ethnicity | E7: pct_inactive_60min_5days, pct_no_pe_classes, pct_no_sports_team, pct_no_daily_pe, pct_inactive_all_days | F7: =_xlfn.XLOOKUP(B7, Parquets!K$2:K$10, Parquets!J$2:J$10) -> yrbss_state_age_demographics.parquet
A8: Nutrition | B8: YRBSS | C8: State | D8: sex, race, ethnicity | E8: pct_no_breakfast, pct_no_breakfast_7days, pct_no_fruit, pct_no_vegetables | F8: =_xlfn.XLOOKUP(B8, Parquets!K$2:K$10, Parquets!J$2:J$10) -> yrbss_state_age_demographics.parquet
B9: medicaid_quality | C9: State | D9: sex, race, ethnicity | E9: medicaid_wcc_ch_rate | F9: =_xlfn.XLOOKUP(B9, Parquets!K$2:K$10, Parquets!J$2:J$10) -> medicaid_state_payer.parquet
B10: CHR | C10: County | E10: chr_limited_access_to_healthy_foods, chr_food_environment_index | F10: =_xlfn.XLOOKUP(B10, Parquets!K$2:K$10, Parquets!J$2:J$10) -> chr_state.parquet, chr_county.parquet | G10: Age baked in

Sheet Social determinants of health
A1: Focus area | B1: Dataset Source | C1: Geographic resolution | D1: Demographic resolution(s) *all have age unless noted | E1: Variables | F1: Parquet file(s) | G1: Notes
A2: Schools | B2: CHR | C2: County | E2: chr_high_school_completion, chr_school_segregation, chr_school_funding_adequacy, chr_child_care_centers, chr_high_school_graduation, chr_math_scores, chr_reading_scores | F2: =_xlfn.XLOOKUP(B2, Parquets!K$2:K$10, Parquets!J$2:J$10) -> chr_state.parquet, chr_county.parquet
A3: Access to care | B3: CHR | C3: County | E3: chr_uninsured_children, chr_primary_care_physicians, chr_inadequate_social_support, chr_other_primary_care_providers | F3: =_xlfn.XLOOKUP(B3, Parquets!K$2:K$10, Parquets!J$2:J$10) -> chr_state.parquet, chr_county.parquet
A4: Poverty measures | B4: CHR | C4: County | E4: chr_children_in_poverty, chr_income_inequality, chr_food_insecurity, | F4: =_xlfn.XLOOKUP(B4, Parquets!K$2:K$10, Parquets!J$2:J$10) -> chr_state.parquet, chr_county.parquet
A5: Housing | B5: CHR | C5: County | E5: chr_single_parent_households, chr_high_housing_costs, chr_severe_housing_problems, chr_severe_housing_cost_burden | F5: =_xlfn.XLOOKUP(B5, Parquets!K$2:K$10, Parquets!J$2:J$10) -> chr_state.parquet, chr_county.parquet
A6: Surrounding communtiy | B6: CHR | C6: County | E6: chr_access_to_recreational_facilities, chr_limited_access_to_healthy_foods, chr_access_to_parks, chr_access_to_exercise_opportunities, chr_food_environment_index, chr_residential_segregation_black_white | F6: =_xlfn.XLOOKUP(B6, Parquets!K$2:K$10, Parquets!J$2:J$10) -> chr_state.parquet, chr_county.parquet
A7: Crime/violence | B7: CHR | C7: County | E7: chr_violent_crime, chr_juvenile_arrests, chr_firearm_fatalities | F7: =_xlfn.XLOOKUP(B7, Parquets!K$2:K$10, Parquets!J$2:J$10) -> chr_state.parquet, chr_county.parquet
